behave_utils/__init__.py
behave_utils/behave.py
behave_utils/binaries.py
behave_utils/docker.py
behave_utils/http.py
behave_utils/init.sql
behave_utils/json.py
behave_utils/mysql.py
behave_utils/proc.py
behave_utils/py.typed
behave_utils/secret.py
behave_utils/types.pyi
behave_utils/url.py
behave_utils/utils.py
behave-stubs/__init__.pyi
behave-stubs/capture.pyi
behave-stubs/fixture.pyi
behave-stubs/formatter/__init__.pyi
behave-stubs/formatter/base.pyi
behave-stubs/log_capture.pyi
behave-stubs/matchers.pyi
behave-stubs/model.pyi
behave-stubs/model_core.pyi
behave-stubs/runner.pyi
behave-stubs/step_registry.pyi
behave-stubs/tag_expression.pyi
behave_utils-0.6.1.dist-info/LICENCE.txt
behave_utils-0.6.1.dist-info/METADATA
behave_utils-0.6.1.dist-info/WHEEL
behave_utils-0.6.1.dist-info/RECORD
