Metadata-Version: 2.1
Name: behave-utils
Version: 0.6.1
Summary: Utilities for writing Behave step implementations
Home-page: https://code.kodo.org.uk/dom/behave-utils
License: MPL-2.0
Author: Dominik Sekotill
Author-email: dom.sekotill@kodo.org.uk
Requires-Python: >=3.10,<4.0
Classifier: Development Status :: 3 - Alpha
Classifier: License :: OSI Approved
Classifier: Programming Language :: Python :: 3
Classifier: Programming Language :: Python :: 3.10
Classifier: Programming Language :: Python :: 3.11
Classifier: Programming Language :: Python :: 3.12
Classifier: Topic :: Software Development :: Testing
Classifier: Topic :: Software Development :: Testing :: BDD
Classifier: Typing :: Typed
Requires-Dist: behave (>=1.2,<2.0)
Requires-Dist: jsonpath-python (>=1.0,<2.0)
Requires-Dist: orjson (>=3.6,<4.0)
Requires-Dist: packaging (>=21)
Requires-Dist: parse (>=1.19,<2.0)
Requires-Dist: requests (>=2.26,<3.0)
Requires-Dist: trio (>=0.25.0,<0.26.0)
Requires-Dist: xdg-base-dirs (>=6.0,<7.0)
Project-URL: Issues, https://code.kodo.org.uk/dom/behave-utils/-/issues
Project-URL: Repository, https://code.kodo.org.uk/dom/behave-utils
